CHANGES.rst
LICENSE
MANIFEST.in
README.rst
morepath_sqlalchemy.db
setup.cfg
setup.py
tox.ini
morepath_sqlalchemy/__init__.py
morepath_sqlalchemy/app.py
morepath_sqlalchemy/collection.py
morepath_sqlalchemy/model.py
morepath_sqlalchemy/path.py
morepath_sqlalchemy/run.py
morepath_sqlalchemy/view.py
morepath_sqlalchemy.egg-info/PKG-INFO
morepath_sqlalchemy.egg-info/SOURCES.txt
morepath_sqlalchemy.egg-info/dependency_links.txt
morepath_sqlalchemy.egg-info/entry_points.txt
morepath_sqlalchemy.egg-info/not-zip-safe
morepath_sqlalchemy.egg-info/requires.txt
morepath_sqlalchemy.egg-info/top_level.txt
morepath_sqlalchemy/tests/__init__.py
morepath_sqlalchemy/tests/test_sqlalchemy.py